juxt/__init__.py
juxt-0.0.1.dist-info/METADATA
juxt-0.0.1.dist-info/WHEEL
juxt-0.0.1.dist-info/RECORD
