Metadata-Version: 2.1
Name: juxt
Version: 0.0.1
Requires-Python: >=3.8
Provides-Extra: dev
Requires-Dist: pyright; extra == 'dev'
Requires-Dist: ruff; extra == 'dev'
